setup.py
genologics_sql/__init__.py
genologics_sql/queries.py
genologics_sql/tables.py
genologics_sql/utils.py
genologics_sql.egg-info/PKG-INFO
genologics_sql.egg-info/SOURCES.txt
genologics_sql.egg-info/dependency_links.txt
genologics_sql.egg-info/entry_points.txt
genologics_sql.egg-info/not-zip-safe
genologics_sql.egg-info/requires.txt
genologics_sql.egg-info/top_level.txt